{"01001": "Danish", "01002": "Danish", "01005": "Danish", "01015": "Danish", "01017": "Danish", "01020": "Danish", "01025": "Danish", "01035": "Danish", "01037": "Danish", "01125": "Danish", "01237": "Danish", "01666": "Danish", "01901": "Danish", "01904": "Danish", "01910": "Danish", "01915": "Danish", "01920": "Danish", "02002": "Danish", "02100": "Danish", "02104": "Danish", "02122": "Danish", "02123": "Danish", "02128": "Danish", "02132": "Danish", "02138": "Danish", "02161": "Danish", "02182": "Danish", "02316": "Danish", "02318": "Danish", "02320": "Danish", "02321": "Danish", "02322": "Danish", "02323": "Danish", "02326": "Danish", "02332": "Danish", "02346": "Danish", "02362": "Danish", "02363": "Danish", "02402": "Danish", "02403": "Danish", "02405": "Danish", "02461": "Danish", "02463": "Danish", "02466": "Danish", "02525": "Danish", "10020": "Danish", "10022": "Danish", "10024": "Danish", "10031": "Danish", "10033": "Danish", "10034": "Danish", "10035": "Danish", "10036": "Danish", "10037": "Danish", "10050": "Danish", "10054": "Danish", "10060": "Danish", "10065": "Danish", "10102": "Danish", "10208": "Danish", "10331": "Danish", "10402": "Danish", "10870": "Danish", "10916": "Danish", "10935": "Danish", "12000": "Danish", "12003": "Danish", "12202": "Danish", "12203": "Danish", "12350": "Danish", "12410": "Danish", "12550": "Danish", "12551": "Danish", "12601": "Danish", "12603": "Danish", "12604": "Danish", "12821": "Danish", "12831": "Danish", "12832": "Danish", "12836": "Danish", "22050": "Danish", "22060": "Danish", "22061": "Danish", "22180": "Danish", "22437": "Danish", "22438": "Danish", "22439": "Danish", "22510": "Danish", "23214": "Danish", "23220": "Danish", "23732": "Danish", "23901": "Danish", "23902": "Danish", "23925": "Danish", "23926": "Danish", "23932": "Danish", "23936": "Danish", "23937": "Danish", "23952": "Danish", "23953": "Danish", "23963": "Danish", "23982": "Danish", "KU304": "Danish", "KU307": "Danish", "25201": "Danish", "25202": "Danish", "25203": "Danish", "25204": "Danish", "25205": "Danish", "25206": "Danish", "25207": "Danish", "25209": "Danish", "25211": "Danish", "25212": "Danish", "26001": "Danish", "26008": "Danish", "26010": "Danish", "26021": "Danish", "26022": "Danish", "26050": "Danish", "26124": "Danish", "26171": "Danish", "26173": "Danish", "26174": "Danish", "26200": "Danish", "26201": "Danish", "26220": "Danish", "26222": "Danish", "26271": "Danish", "26300": "Danish", "26371": "Danish", "26374": "Danish", "26400": "Danish", "26411": "Danish", "26471": "Danish", "26800": "Danish", "27002": "Danish", "28010": "Danish", "28012": "Danish", "28016": "Danish", "28020": "Danish", "28022": "Danish", "28322": "Danish", "28342": "Danish", "28352": "Danish", "30010": "Danish", "30015": "Danish", "30020": "Danish", "30032": "Danish", "30081": "Danish", "30082": "Danish", "30100": "Danish", "30110": "Danish", "30120": "Danish", "30131": "Danish", "30142": "Danish", "30150": "Danish", "30160": "Danish", "30531": "Danish", "34019": "Danish", "34021": "Danish", "34029": "Danish", "34038": "Danish", "34120": "Danish", "34210": "Danish", "34220": "Danish", "34302": "Danish", "34313": "Danish", "34318": "Danish", "34324": "Danish", "34331": "Danish", "34332": "Danish", "34333": "Danish", "34334": "Danish", "34600": "Danish", "34601": "Danish", "34720": "Danish", "41000": "Danish", "41012": "Danish", "41015": "Danish", "41020": "Danish", "41028": "Danish", "41029": "Danish", "41045": "Danish", "41102": "Danish", "41112": "Danish", "41201": "Danish", "41204": "Danish", "41236": "Danish", "41263": "Danish", "41270": "Danish", "41280": "Danish", "41402": "Danish", "41422": "Danish", "41451": "Danish", "41452": "Danish", "41458": "Danish", "41459": "Danish", "41501": "Danish", "41502": "Danish", "41533": "Danish", "41534": "Danish", "41564": "Danish", "41603": "Danish", "41612": "Danish", "41619": "Danish", "41651": "Danish", "41659": "Danish", "41681": "Danish", "41686": "Danish", "41687": "Danish", "41689": "Danish", "41714": "Danish", "41784": "Danish", "41787": "Danish", "41801": "Danish", "41843": "Danish", "41860": "Danish", "41861": "Danish", "41862": "Danish", "41863": "Danish", "41871": "Danish", "41872": "Danish", "41873": "Danish", "41874": "Danish", "41876": "Danish", "41903": "Danish", "41905": "Danish", "41906": "Danish", "41911": "Danish", "41919": "Danish", "41925": "Danish", "41927": "Danish", "41928": "Danish", "41929": "Danish", "41941": "Danish", "41942": "Danish", "41943": "Danish", "41944": "Danish", "41945": "Danish", "41946": "Danish", "41947": "Danish", "41948": "Danish", "41951": "Danish", "41953": "Danish", "41954": "Danish", "41955": "Danish", "41956": "Danish", "41957": "Danish", "41958": "Danish", "41B01": "Danish", "41B02": "Danish", "41B03": "Danish", "41B04": "Danish", "41B13": "Danish", "41B1A": "Danish", "41B1B": "Danish", "41B1C": "Danish", "41B24": "Danish", "41B25": "Danish", "41B27": "Danish", "41B2A": "Danish", "41B2B": "Danish", "41B2C": "Danish", "41E16": "Danish", "41MIB": "Danish", "42011": "Danish", "42042": "Danish", "42580": "Danish", "42584": "Danish", "42587": "Danish", "42588": "Danish", "42973": "Danish", "46015": "Danish", "46020": "Danish", "46025": "Danish", "46030": "Danish", "46050": "Danish", "88383": "Danish", "KU002": "Danish", "KU003": "Danish", "KU004": "Danish", "KU006": "Danish", "KU010": "Danish", "KU011": "Danish", "62000": "Danish", "62001": "Danish", "62009": "Danish", "62014": "Danish", "62024": "Danish", "62030": "Danish", "62033": "Danish", "62039": "Danish", "62041": "Danish", "62048": "Danish", "62051": "Danish", "62054": "Danish", "62074": "Danish", "62079": "Danish", "62087": "Danish", "62096": "Danish", "62101": "Danish", "62104": "Danish", "62107": "Danish", "62108": "Danish", "62111": "Danish", "62118": "Danish", "62119": "Danish", "62120": "Danish", "62142": "Danish", "62145": "Danish", "62146": "Danish", "62168": "Danish", "62169": "Danish", "62174": "Danish", "62191": "Danish", "62199": "Danish", "62206": "Danish", "62207": "Danish", "62210": "Danish", "62218": "Danish", "62223": "Danish", "62229": "Danish", "62231": "Danish", "62233": "Danish", "62234": "Danish", "62243": "Danish", "62249": "Danish", "62261": "Danish", "62263": "Danish", "62265": "Danish", "62267": "Danish", "62268": "Danish", "62269": "Danish", "62271": "Danish", "62272": "Danish", "62273": "Danish", "62276": "Danish", "62277": "Danish", "62279": "Danish", "62281": "Danish", "62319": "Danish", "62320": "Danish", "62324": "Danish", "62327": "Danish", "62328": "Danish", "62330": "Danish", "62331": "Danish", "62333": "Danish", "62369": "Danish", "62381": "Danish", "62410": "Danish", "62416": "Danish", "62420": "Danish", "62422": "Danish", "62423": "Danish", "62426": "Danish", "62427": "Danish", "62428": "Danish", "62443": "Danish", "62450": "Danish", "62452": "Danish", "62453": "Danish", "62454": "Danish", "62484": "Danish", "62512": "Danish", "62517": "Danish", "62521": "Danish", "62523": "Danish", "62525": "Danish", "62532": "Danish", "62560": "Danish", "62575": "Danish", "62577": "Danish", "62581": "Danish", "62582": "Danish", "62589": "Danish", "62597": "Danish", "62604": "Danish", "62616": "Danish", "62617": "Danish", "62623": "Danish", "62640": "Danish", "62646": "Danish", "62657": "Danish", "62664": "Danish", "62675": "Danish", "62677": "Danish", "62683": "Danish", "62694": "Danish", "62696": "Danish", "62705": "Danish", "62708": "Danish", "62711": "Danish", "62733": "Danish", "62734": "Danish", "62735": "Danish", "62739": "Danish", "62743": "Danish", "62748": "Danish", "62751": "Danish", "62752": "Danish", "62753": "Danish", "62762": "Danish", "62763": "Danish", "62764": "Danish", "62768": "Danish", "62773": "Danish", "62774": "Danish", "62783": "Danish", "62798": "Danish", "62800": "Danish", "62801": "Danish", "62802": "Danish", "62803": "Danish", "62805": "Danish", "62806": "Danish", "62807": "Danish", "62908": "Danish", "62B01": "Danish", "62B02": "Danish", "62B03": "Danish", "62B06": "Danish", "62B20": "Danish", "62B24": "Danish", "62B29": "Danish", "62B90": "Danish", "62C02": "Danish", "62C05": "Danish", "62C09": "Danish", "62C21": "Danish", "62C30": "Danish", "62C90": "Danish", "62E90": "Danish", "62I01": "Danish", "62I02": "Danish", "62I03": "Danish", "62I04": "Danish", "62I05": "Danish", "62I07": "Danish", "62I08": "Danish", "62I10": "Danish", "62I11": "Danish", "62I12": "Danish", "62I14": "Danish", "62I15": "Danish", "62I16": "Danish", "62I18": "Danish", "62I19": "Danish", "62I90": "Danish", "62K01": "Danish", "62K02": "Danish", "62K03": "Danish", "62L01": "Danish", "62L02": "Danish", "62L03": "Danish", "62L04": "Danish", "62L05": "Danish", "62L06": "Danish", "62L07": "Danish", "62L10": "Danish", "62L12": "Danish", "62L13": "Danish", "62L15": "Danish", "62L16": "Danish", "62L17": "Danish", "62L18": "Danish", "62L23": "Danish", "62L29": "Danish", "62L32": "Danish", "62L33": "Danish", "62L36": "Danish", "62L40": "Danish", "62L67": "Danish", "62L79": "Danish", "62L84": "Danish", "62L85": "Danish", "62L89": "Danish", "62L90": "Danish", "62L91": "Danish", "62L92": "Danish", "62L93": "Danish", "62L94": "Danish", "62P01": "Danish", "62P02": "Danish", "62P03": "Danish", "62P04": "Danish", "62P07": "Danish", "62P08": "Danish", "62P36": "Danish", "62P37": "Danish", "62P90": "Danish", "62P91": "Danish", "62T01": "Danish", "62T04": "Danish", "62T20": "Danish", "62T25": "Danish", "62T26": "Danish", "62T34": "Danish", "62T37": "Danish", "62T38": "Danish", "62T39": "Danish", "62T90": "Danish", "01003": "English", "01004": "English", "01006": "English", "01018": "English", "01019": "English", "01034": "English", "01227": "English", "01238": "English", "01257": "English", "01325": "English", "01405": "English", "01410": "English", "01415": "English", "01418": "English", "01426": "English", "01527": "English", "01617": "English", "01621": "English", "01622": "English", "01715": "English", "01716": "English", "02003": "English", "02105": "English", "02110": "English", "02112": "English", "02113": "English", "02114": "English", "02116": "English", "02118": "English", "02135": "English", "02139": "English", "02141": "English", "02143": "English", "02148": "English", "02155": "English", "02156": "English", "02157": "English", "02158": "English", "02159": "English", "02160": "English", "02162": "English", "02170": "English", "02180": "English", "02191": "English", "02192": "English", "02193": "English", "02195": "English", "02196": "English", "02201": "English", "02203": "English", "02204": "English", "02205": "English", "02209": "English", "02211": "English", "02214": "English", "02223": "English", "02224": "English", "02226": "English", "02232": "English", "02233": "English", "02234": "English", "02238": "English", "02239": "English", "02242": "English", "02244": "English", "02245": "English", "02246": "English", "02247": "English", "02249": "English", "02255": "English", "02256": "English", "02257": "English", "02258": "English", "02263": "English", "02266": "English", "02267": "English", "02268": "English", "02269": "English", "02282": "English", "02285": "English", "02287": "English", "02289": "English", "02291": "English", "02314": "English", "02317": "English", "02324": "English", "02327": "English", "02335": "English", "02369": "English", "02393": "English", "02407": "English", "02409": "English", "02411": "English", "02413": "English", "02417": "English", "02418": "English", "02421": "English", "02424": "English", "02425": "English", "02427": "English", "02429": "English", "02431": "English", "02435": "English", "02441": "English", "02443": "English", "02445": "English", "02450": "English", "02455": "English", "02456": "English", "02458": "English", "02460": "English", "02462": "English", "02464": "English", "02465": "English", "02467": "English", "02471": "English", "02476": "English", "02477": "English", "02492": "English", "02501": "English", "02502": "English", "02504": "English", "02506": "English", "02509": "English", "02510": "English", "02516": "English", "02526": "English", "02561": "English", "02562": "English", "02563": "English", "02566": "English", "02580": "English", "02582": "English", "02586": "English", "02601": "English", "02610": "English", "02612": "English", "02613": "English", "02614": "English", "02616": "English", "02619": "English", "02623": "English", "02624": "English", "02635": "English", "02686": "English", "02687": "English", "02689": "English", "02805": "English", "02806": "English", "02807": "English", "02808": "English", "02809": "English", "02830": "English", "02840": "English", "02841": "English", "02901": "English", "02910": "English", "02913": "English", "02935": "English", "02940": "English", "02941": "English", "02946": "English", "02949": "English", "02953": "English", "02955": "English", "02960": "English", "02975": "English", "02979": "English", "02980": "English", "02981": "English", "02982": "English", "02985": "English", "02G01": "English", "02G02": "English", "02G03": "English", "02G04": "English", "02G05": "English", "02G06": "English", "02G07": "English", "02G08": "English", "02G09": "English", "02G10": "English", "10041": "English", "10063": "English", "10080": "English", "10104": "English", "10112": "English", "10122": "English", "10200": "English", "10209": "English", "10240": "English", "10255": "English", "10260": "English", "10302": "English", "10303": "English", "10304": "English", "10306": "English", "10314": "English", "10315": "English", "10316": "English", "10317": "English", "10318": "English", "10321": "English", "10325": "English", "10326": "English", "10333": "English", "10337": "English", "10339": "English", "10346": "English", "10350": "English", "10380": "English", "10384": "English", "10385": "English", "10386": "English", "10387": "English", "10400": "English", "10401": "English", "10405": "English", "10411": "English", "10413": "English", "10420": "English", "10506": "English", "10507": "English", "10508": "English", "10509": "English", "10511": "English", "10512": "English", "10514": "English", "10515": "English", "10519": "English", "10520": "English", "10521": "English", "10530": "English", "10540": "English", "10550": "English", "10590": "English", "10603": "English", "10605": "English", "10610": "English", "10720": "English", "10721": "English", "10722": "English", "10730": "English", "10731": "English", "10732": "English", "10750": "English", "10850": "English", "10851": "English", "10852": "English", "10855": "English", "10862": "English", "10871": "English", "12100": "English", "12102": "English", "12104": "English", "12109": "English", "12110": "English", "12111": "English", "12121": "English", "12122": "English", "12124": "English", "12130": "English", "12132": "English", "12134": "English", "12139": "English", "12143": "English", "12145": "English", "12205": "English", "12211": "English", "12227": "English", "12228": "English", "12231": "English", "12237": "English", "12238": "English", "12240": "English", "12245": "English", "12250": "English", "12320": "English", "12330": "English", "12331": "English", "12336": "English", "12345": "English", "12360": "English", "12361": "English", "12362": "English", "12363": "English", "12411": "English", "12412": "English", "12415": "English", "12421": "English", "12422": "English", "12423": "English", "12430": "English", "12431": "English", "12432": "English", "12451": "English", "12452": "English", "12552": "English", "12605": "English", "12611": "English", "12612": "English", "12614": "English", "12701": "English", "12772": "English", "12773": "English", "12774": "English", "12854": "English", "12859": "English", "12902": "English", "12911": "English", "12919": "English", "12920": "English", "12936": "English", "12940": "English", "12941": "English", "12950": "English", "12951": "English", "12952": "English", "12953": "English", "12954": "English", "22000": "English", "22001": "English", "22002": "English", "22003": "English", "22004": "English", "22005": "English", "22051": "English", "22052": "English", "22053": "English", "22054": "English", "22057": "English", "22100": "English", "22101": "English", "22102": "English", "22107": "English", "22111": "English", "22112": "English", "22113": "English", "22115": "English", "22117": "English", "22123": "English", "22125": "English", "22126": "English", "22140": "English", "22145": "English", "22160": "English", "22161": "English", "22163": "English", "22175": "English", "22179": "English", "22201": "English", "22202": "English", "22203": "English", "22205": "English", "22206": "English", "22207": "English", "22208": "English", "22210": "English", "22211": "English", "22230": "English", "22231": "English", "22232": "English", "22235": "English", "22236": "English", "22237": "English", "22281": "English", "22282": "English", "22283": "English", "22284": "English", "22285": "English", "22400": "English", "22403": "English", "22435": "English", "22446": "English", "22481": "English", "22485": "English", "22486": "English", "22487": "English", "22506": "English", "22507": "English", "22508": "English", "22511": "English", "22512": "English", "22513": "English", "22525": "English", "22530": "English", "22600": "English", "22602": "English", "22603": "English", "22604": "English", "22610": "English", "22611": "English", "22612": "English", "22652": "English", "22656": "English", "22680": "English", "22681": "English", "22800": "English", "23101": "English", "23102": "English", "23205": "English", "23206": "English", "23210": "English", "23212": "English", "23216": "English", "23255": "English", "23256": "English", "23257": "English", "23258": "English", "23260": "English", "23261": "English", "23262": "English", "23263": "English", "23272": "English", "23301": "English", "23302": "English", "23360": "English", "23511": "English", "23520": "English", "23521": "English", "23522": "English", "23531": "English", "23532": "English", "23552": "English", "23564": "English", "23662": "English", "23711": "English", "23832": "English", "23837": "English", "23839": "English", "23841": "English", "23842": "English", "23F11": "English", "23F12": "English", "23F13": "English", "23F14": "English", "23F15": "English", "23F16": "English", "KU320": "English", "KU321": "English", "KU322": "English", "KU323": "English", "25102": "English", "25104": "English", "25105": "English", "25106": "English", "25107": "English", "25108": "English", "25208": "English", "25210": "English", "25302": "English", "25303": "English", "25310": "English", "25311": "English", "25312": "English", "25313": "English", "25314": "English", "25315": "English", "25316": "English", "25317": "English", "25318": "English", "25321": "English", "25322": "English", "25323": "English", "25324": "English", "25325": "English", "25326": "English", "25327": "English", "25328": "English", "25331": "English", "25334": "English", "25335": "English", "25336": "English", "25340": "English", "25341": "English", "25342": "English", "25343": "English", "25344": "English", "25345": "English", "25346": "English", "25347": "English", "25348": "English", "25349": "English", "25350": "English", "25616": "English", "25617": "English", "25618": "English", "25619": "English", "25621": "English", "25622": "English", "25801": "English", "25803": "English", "25805": "English", "25807": "English", "25808": "English", "25809": "English", "25811": "English", "25812": "English", "25813": "English", "25814": "English", "25815": "English", "25816": "English", "25817": "English", "25818": "English", "25819": "English", "25820": "English", "25821": "English", "25822": "English", "25823": "English", "25824": "English", "25825": "English", "25826": "English", "25827": "English", "25829": "English", "25830": "English", "25831": "English", "25832": "English", "26002": "English", "26003": "English", "26004": "English", "26020": "English", "26125": "English", "26127": "English", "26130": "English", "26134": "English", "26211": "English", "26225": "English", "26231": "English", "26236": "English", "26245": "English", "26255": "English", "26261": "English", "26263": "English", "26280": "English", "26290": "English", "26317": "English", "26407": "English", "26416": "English", "26422": "English", "26426": "English", "26428": "English", "26433": "English", "26436": "English", "26438": "English", "26444": "English", "26446": "English", "26455": "English", "26474": "English", "26510": "English", "26620": "English", "26701": "English", "26702": "English", "26932": "English", "26933": "English", "26944": "English", "26970": "English", "26991": "English", "27016": "English", "27020": "English", "27022": "English", "27023": "English", "27026": "English", "27027": "English", "27034": "English", "27035": "English", "27051": "English", "27062": "English", "27070": "English", "27075": "English", "27101": "English", "27220": "English", "27230": "English", "27246": "English", "27247": "English", "27255": "English", "27325": "English", "27330": "English", "27410": "English", "27419": "English", "27422": "English", "27423": "English", "27430": "English", "27432": "English", "27455": "English", "27460": "English", "27470": "English", "27472": "English", "27510": "English", "27665": "English", "27691": "English", "27692": "English", "27800": "English", "27801": "English", "27820": "English", "27823": "English", "27828": "English", "27832": "English", "27838": "English", "27839": "English", "27845": "English", "28025": "English", "28121": "English", "28123": "English", "28125": "English", "28140": "English", "28150": "English", "28157": "English", "28160": "English", "28212": "English", "28213": "English", "28214": "English", "28216": "English", "28217": "English", "28221": "English", "28233": "English", "28242": "English", "28244": "English", "28271": "English", "28311": "English", "28315": "English", "28316": "English", "28344": "English", "28345": "English", "28346": "English", "28350": "English", "28361": "English", "28412": "English", "28420": "English", "28423": "English", "28434": "English", "28443": "English", "28451": "English", "28455": "English", "28485": "English", "28515": "English", "28530": "English", "28720": "English", "28737": "English", "28745": "English", "28761": "English", "28811": "English", "28831": "English", "28845": "English", "28850": "English", "28852": "English", "28855": "English", "28857": "English", "28864": "English", "28870": "English", "28871": "English", "28872": "English", "28885": "English", "28905": "English", "28908": "English", "28909": "English", "28917": "English", "28923": "English", "28927": "English", "28928": "English", "28930": "English", "28932": "English", "28933": "English", "28934": "English", "88704": "English", "88709": "English", "88710": "English", "88717": "English", "29902": "English", "29903": "English", "29905": "English", "29906": "English", "30021": "English", "30035": "English", "30202": "English", "30220": "English", "30230": "English", "30300": "English", "30310": "English", "30320": "English", "30330": "English", "30340": "English", "30350": "English", "30400": "English", "30405": "English", "30415": "English", "30420": "English", "30428": "English", "30430": "English", "30510": "English", "30530": "English", "30540": "English", "30545": "English", "30552": "English", "30554": "English", "30561": "English", "30564": "English", "30574": "English", "30710": "English", "30720": "English", "30745": "English", "30752": "English", "30755": "English", "30757": "English", "30760": "English", "30790": "English", "30794": "English", "30857": "English", "30911": "English", "30970": "English", "34020": "English", "34023": "English", "34024": "English", "34031": "English", "34032": "English", "34034": "English", "34041": "English", "34042": "English", "34043": "English", "34046": "English", "34051": "English", "34052": "English", "34053": "English", "34060": "English", "34061": "English", "34091": "English", "34092": "English", "34094": "English", "34121": "English", "34126": "English", "34127": "English", "34129": "English", "34130": "English", "34153": "English", "34156": "English", "34190": "English", "34192": "English", "34193": "English", "34194": "English", "34229": "English", "34230": "English", "34240": "English", "34241": "English", "34249": "English", "34250": "English", "34251": "English", "34269": "English", "34290": "English", "34315": "English", "34322": "English", "34323": "English", "34325": "English", "34338": "English", "34343": "English", "34345": "English", "34346": "English", "34349": "English", "34351": "English", "34359": "English", "34365": "English", "34366": "English", "34367": "English", "34368": "English", "34369": "English", "34370": "English", "34371": "English", "34373": "English", "34430": "English", "34440": "English", "34451": "English", "34492": "English", "34495": "English", "34539": "English", "34540": "English", "34541": "English", "34551": "English", "34552": "English", "34553": "English", "34590": "English", "34602": "English", "34620": "English", "34630": "English", "34652": "English", "34653": "English", "34654": "English", "34655": "English", "34656": "English", "34657": "English", "34658": "English", "34659": "English", "34690": "English", "34721": "English", "34722": "English", "34723": "English", "34724": "English", "34745": "English", "34746": "English", "34748": "English", "34752": "English", "34753": "English", "34755": "English", "34757": "English", "34759": "English", "34760": "English", "34761": "English", "34762": "English", "34763": "English", "34791": "English", "34792": "English", "34840": "English", "34844": "English", "34846": "English", "34847": "English", "34848": "English", "34850": "English", "34860": "English", "34865": "English", "34867": "English", "34870": "English", "34871": "English", "34880": "English", "34895": "English", "41011": "English", "41013": "English", "41031": "English", "41051": "English", "41073": "English", "41083": "English", "41084": "English", "41107": "English", "41111": "English", "41113": "English", "41117": "English", "41126": "English", "41129": "English", "41216": "English", "41222": "English", "41226": "English", "41237": "English", "41271": "English", "41275": "English", "41292": "English", "41312": "English", "41315": "English", "41316": "English", "41317": "English", "41320": "English", "41321": "English", "41341": "English", "41342": "English", "41343": "English", "41346": "English", "41347": "English", "41391": "English", "41392": "English", "41401": "English", "41416": "English", "41417": "English", "41418": "English", "41420": "English", "41461": "English", "41462": "English", "41463": "English", "41464": "English", "41465": "English", "41466": "English", "41467": "English", "41468": "English", "41490": "English", "41491": "English", "41511": "English", "41512": "English", "41514": "English", "41515": "English", "41516": "English", "41517": "English", "41522": "English", "41524": "English", "41525": "English", "41526": "English", "41528": "English", "41561": "English", "41563": "English", "41591": "English", "41615": "English", "41635": "English", "41636": "English", "41637": "English", "41638": "English", "41639": "English", "41653": "English", "41656": "English", "41658": "English", "41661": "English", "41662": "English", "41667": "English", "41668": "English", "41669": "English", "41680": "English", "41684": "English", "41685": "English", "41690": "English", "41691": "English", "41730": "English", "41733": "English", "41734": "English", "41735": "English", "41737": "English", "41739": "English", "41740": "English", "41743": "English", "41747": "English", "41748": "English", "41749": "English", "41789": "English", "41791": "English", "41792": "English", "41808": "English", "41812": "English", "41813": "English", "41814": "English", "41822": "English", "41831": "English", "41832": "English", "41881": "English", "41882": "English", "41931": "English", "41932": "English", "41933": "English", "41934": "English", "41935": "English", "41936": "English", "41937": "English", "41938": "English", "41952": "English", "41961": "English", "41963": "English", "41964": "English", "41965": "English", "41967": "English", "41968": "English", "41969": "English", "41970": "English", "41B05": "English", "41B12": "English", "38001": "English", "38102": "English", "38103": "English", "38104": "English", "38105": "English", "38106": "English", "38107": "English", "38108": "English", "38109": "English", "38110": "English", "38111": "English", "38201": "English", "38202": "English", "38203": "English", "38204": "English", "38301": "English", "38302": "English", "38303": "English", "38799": "English", "42001": "English", "42009": "English", "42014": "English", "42015": "English", "42016": "English", "42101": "English", "42112": "English", "42114": "English", "42115": "English", "42117": "English", "42136": "English", "42137": "English", "42142": "English", "42146": "English", "42147": "English", "42178": "English", "42180": "English", "42186": "English", "42187": "English", "42380": "English", "42382": "English", "42402": "English", "42404": "English", "42417": "English", "42421": "English", "42500": "English", "42501": "English", "42502": "English", "42503": "English", "42504": "English", "42505": "English", "42543": "English", "42576": "English", "42577": "English", "42578": "English", "42586": "English", "42620": "English", "42622": "English", "42701": "English", "42702": "English", "42787": "English", "42879": "English", "42893": "English", "42B50": "English", "42B51": "English", "42B54": "English", "42B55": "English", "42B56": "English", "42B61": "English", "42B67": "English", "42B68": "English", "42B71": "English", "42B73": "English", "42B76": "English", "42B77": "English", "42B84": "English", "42B85": "English", "42B86": "English", "42B87": "English", "42B88": "English", "42B90": "English", "42B91": "English", "42B92": "English", "42MMT": "English", "42S01": "English", "42S02": "English", "42S03": "English", "42S04": "English", "42S05": "English", "42S06": "English", "42S07": "English", "42S08": "English", "42S09": "English", "42S10": "English", "46000": "English", "46035": "English", "46040": "English", "46045": "English", "46055": "English", "46060": "English", "46100": "English", "46110": "English", "46115": "English", "46200": "English", "46205": "English", "46211": "English", "46215": "English", "46230": "English", "46300": "English", "46310": "English", "46320": "English", "46400": "English", "46411": "English", "46415": "English", "46420": "English", "46440": "English", "46500": "English", "46550": "English", "46600": "English", "46610": "English", "46700": "English", "46705": "English", "46710": "English", "46715": "English", "46720": "English", "46725": "English", "46735": "English", "46740": "English", "46745": "English", "46750": "English", "46755": "English", "46760": "English", "46765": "English", "46770": "English", "46795": "English", "46797": "English", "46901": "English", "46905": "English", "46910": "English", "46915": "English", "46920": "English", "46W11": "English", "46W14": "English", "46W17": "English", "46W21": "English", "46W24": "English", "46W27": "English", "46W31": "English", "46W34": "English", "46W37": "English", "46W44": "English", "46W47": "English", "47201": "English", "47202": "English", "47203": "English", "47205": "English", "47209": "English", "47211": "English", "47212": "English", "47213": "English", "47214": "English", "47215": "English", "47301": "English", "47302": "English", "47304": "English", "47305": "English", "47310": "English", "47317": "English", "47319": "English", "47330": "English", "47332": "English", "47333": "English", "47334": "English", "47335": "English", "47336": "English", "47337": "English", "47338": "English", "47339": "English", "47340": "English", "47507": "English", "47508": "English", "47509": "English", "47511": "English", "47513": "English", "47514": "English", "47517": "English", "47519": "English", "47520": "English", "47521": "English", "47522": "English", "47523": "English", "47525": "English", "47526": "English", "47527": "English", "56867": "English", "56868": "English", "KU005": "English", "KU012": "English", "KU101": "English", "KU103": "English", "KU105": "English", "KU112": "English", "KU113": "English", "KU115": "English", "KU180": "English", "KU181": "English", "62008": "English", "62019": "English", "62133": "English", "62134": "English", "62139": "English", "62177": "English", "62198": "English", "62202": "English", "62205": "English", "62211": "English", "62224": "English", "62225": "English", "62235": "English", "62238": "English", "62280": "English", "62282": "English", "62329": "English", "62362": "English", "62366": "English", "62389": "English", "62413": "English", "62417": "English", "62444": "English", "62531": "English", "62533": "English", "62550": "English", "62601": "English", "62614": "English", "62622": "English", "62629": "English", "62637": "English", "62643": "English", "62669": "English", "62704": "English", "62716": "English", "62755": "English", "62756": "English", "62760": "English", "62761": "English", "62766": "English", "62770": "English", "62782": "English", "62990": "English", "62999": "English", "62T22": "English", "63850": "English", "63851": "English", "63852": "English", "63860": "English", "63861": "English", "63880": "English", "63881": "English"}